models/FullyConnected.py
models/__init__.py
trainkit-0.0.1.dist-info/LICENSE.md
trainkit-0.0.1.dist-info/METADATA
trainkit-0.0.1.dist-info/WHEEL
trainkit-0.0.1.dist-info/top_level.txt
trainkit-0.0.1.dist-info/RECORD
